Metadata-Version: 1.0
Name: flask-helloworld
Version: 1.0.0
Summary: Flask Helloworld
Home-page: UNKNOWN
Author: Florian Dambrine
Author-email: android.florian@gmail.com
License: BSD
Keywords: flask
Platform: UNKNOWN
